ujsonpath/VERSION
ujsonpath/__init__.py
ujsonpath/ujsonpath.py
ujsonpath-0.0.2.dist-info/DESCRIPTION.rst
ujsonpath-0.0.2.dist-info/METADATA
ujsonpath-0.0.2.dist-info/RECORD
ujsonpath-0.0.2.dist-info/WHEEL
ujsonpath-0.0.2.dist-info/metadata.json
ujsonpath-0.0.2.dist-info/top_level.txt
