Metadata-Version: 2.0
Name: ujsonpath
Version: 0.0.2
Summary: A fast JSONPath implementation
Home-page: https://github.com/LuizArmesto/ujsonpath
Author: Luiz Armesto
Author-email: luiz.armesto@gmail.com
License: UNKNOWN
Platform: UNKNOWN
Classifier: Development Status :: 3 - Alpha
Classifier: Intended Audience :: Developers
Classifier: Programming Language :: Python
Classifier: Programming Language :: Python :: 2
Classifier: Programming Language :: Python :: 2.7
Classifier: Programming Language :: Python :: 3
Classifier: Programming Language :: Python :: 3.5
